opentelemetry/instrumentation/llamaindex/__init__.py
opentelemetry/instrumentation/llamaindex/callback_handler.py
opentelemetry/instrumentation/llamaindex/config.py
opentelemetry/instrumentation/llamaindex/invocation_manager.py
opentelemetry/instrumentation/llamaindex/vendor_detection.py
opentelemetry/instrumentation/llamaindex/version.py
opentelemetry/instrumentation/llamaindex/workflow_instrumentation.py
splunk_otel_instrumentation_llamaindex-0.1.0.dist-info/METADATA
splunk_otel_instrumentation_llamaindex-0.1.0.dist-info/WHEEL
splunk_otel_instrumentation_llamaindex-0.1.0.dist-info/entry_points.txt
splunk_otel_instrumentation_llamaindex-0.1.0.dist-info/RECORD
