Metadata-Version: 2.4
Name: splunk-otel-instrumentation-llamaindex
Version: 0.1.0
Summary: Splunk OpenTelemetry LlamaIndex instrumentation
Project-URL: Homepage, https://github.com/open-telemetry/opentelemetry-python-contrib/tree/main/instrumentation-genai/opentelemetry-instrumentation-llamaindex
Project-URL: Repository, https://github.com/open-telemetry/opentelemetry-python-contrib
License-Expression: Apache-2.0
Classifier: Development Status :: 4 - Beta
Classifier: Intended Audience :: Developers
Classifier: License :: OSI Approved :: Apache Software License
Classifier: Programming Language :: Python
Classifier: Programming Language :: Python :: 3.9
Classifier: Programming Language :: Python :: 3.10
Classifier: Programming Language :: Python :: 3.11
Classifier: Programming Language :: Python :: 3.12
Classifier: Programming Language :: Python :: 3.13
Requires-Python: >=3.9
Requires-Dist: opentelemetry-api~=1.38.0.dev0
Requires-Dist: opentelemetry-instrumentation~=0.59b0.dev0
Requires-Dist: opentelemetry-semantic-conventions~=0.59b0.dev0
Requires-Dist: splunk-otel-util-genai>=0.1.4
Provides-Extra: instruments
Requires-Dist: llama-index-core>=0.14.0; extra == 'instruments'
Provides-Extra: test
Requires-Dist: llama-index-core>=0.14.0; extra == 'test'
Requires-Dist: llama-index-llms-openai>=0.6.0; extra == 'test'
Requires-Dist: pytest>=7.0.0; extra == 'test'
